csc121/__init__.py
csc121/audio.py
csc121/cached_comments.txt
csc121/cached_tweets.txt
csc121/image.py
csc121/reddit.py
csc121/terminal.py
csc121/twitter.py
csc121-2.0.1.dist-info/METADATA
csc121-2.0.1.dist-info/WHEEL
csc121-2.0.1.dist-info/licenses/LICENSE
csc121-2.0.1.dist-info/RECORD
